{
  "kind": "BACKGROUND",
  "slug": "earthspur-miner",
  "url": "https://dnd5e.wikidot.com/background:earthspur-miner",
  "page_title": "earthspur-miner",
  "aliases": [
    "Earthspur Miner"
  ],
  "categories": [
    "AL: Mulmaster"
  ],
  "content": {
    "format": "html-structure-tree",
    "allowed_tags": [
      "b",
      "blockquote",
      "br",
      "code",
      "em",
      "h1",
      "h2",
      "h3",
      "h4",
      "h5",
      "h6",
      "hr",
      "i",
      "li",
      "ol",
      "p",
      "pre",
      "strong",
      "table",
      "tbody",
      "td",
      "tfoot",
      "th",
      "thead",
      "tr",
      "ul"
    ],
    "tree": [
      {
        "type": "element",
        "tag": "p",
        "children": [
          {
            "type": "text",
            "text": "Source: Mulmaster Bonds and Backgrounds"
          }
        ]
      },
      {
        "type": "element",
        "tag": "p",
        "children": [
          {
            "type": "text",
            "text": "You are a down-on-your-luck miner from the Earthspur Mountains who is no stranger to hardship. You have spent a great deal of time living among the dwarves, goliaths, and denizens of the Underdark who also work mines in the area. At this point, you're just as comfortable working underground as above. You know how to read a seam, dicker for supplies with the deep gnomes, party with dwarves, and find your way back to the surface afterward. Unfortunately, you haven't struck it rich… yet. Although you've come to Mulmaster looking for work, the tall peaks and deep mines of the Earthspurs still call to you."
          }
        ]
      },
      {
        "type": "element",
        "tag": "p",
        "children": [
          {
            "type": "element",
            "tag": "strong",
            "children": [
              {
                "type": "text",
                "text": "Skill Proficiencies:"
              }
            ]
          },
          {
            "type": "text",
            "text": " Athletics, Survival"
          },
          {
            "type": "element",
            "tag": "br",
            "children": []
          },
          {
            "type": "element",
            "tag": "strong",
            "children": [
              {
                "type": "text",
                "text": "Languages:"
              }
            ]
          },
          {
            "type": "text",
            "text": " Dwarven and Undercommon"
          },
          {
            "type": "element",
            "tag": "br",
            "children": []
          },
          {
            "type": "element",
            "tag": "strong",
            "children": [
              {
                "type": "text",
                "text": "Equipment:"
              }
            ]
          },
          {
            "type": "text",
            "text": " A "
          },
          {
            "type": "text",
            "text": "shovel"
          },
          {
            "type": "text",
            "text": "Value:2gp Weight:5lbs"
          },
          {
            "type": "text",
            "text": " or a "
          },
          {
            "type": "text",
            "text": "miner's pick"
          },
          {
            "type": "text",
            "text": "Value:2gp Weight:10lbs"
          },
          {
            "type": "text",
            "text": ", a "
          },
          {
            "type": "text",
            "text": "block and tackle"
          },
          {
            "type": "text",
            "text": "Value:1gp Weight:5lbs"
          },
          {
            "type": "text",
            "text": ", a "
          },
          {
            "type": "text",
            "text": "climber's kit"
          },
          {
            "type": "text",
            "text": "Contents:"
          },
          {
            "type": "element",
            "tag": "br",
            "children": []
          },
          {
            "type": "text",
            "text": " Special Pitons"
          },
          {
            "type": "element",
            "tag": "br",
            "children": []
          },
          {
            "type": "text",
            "text": " Boot Tips"
          },
          {
            "type": "element",
            "tag": "br",
            "children": []
          },
          {
            "type": "text",
            "text": " Gloves"
          },
          {
            "type": "element",
            "tag": "br",
            "children": []
          },
          {
            "type": "text",
            "text": " Harness"
          },
          {
            "type": "text",
            "text": ", a set of "
          },
          {
            "type": "text",
            "text": "common clothes"
          },
          {
            "type": "text",
            "text": "Value:5sp Weight:3lbs"
          },
          {
            "type": "text",
            "text": ", and a "
          },
          {
            "type": "text",
            "text": "pouch"
          },
          {
            "type": "text",
            "text": "Value:5sp Weight:1lb"
          },
          {
            "type": "text",
            "text": " containing 5gp"
          }
        ]
      },
      {
        "type": "element",
        "tag": "h2",
        "children": [
          {
            "type": "text",
            "text": "Feature: Deep Miner"
          }
        ]
      },
      {
        "type": "element",
        "tag": "p",
        "children": [
          {
            "type": "text",
            "text": "You are used to navigating the deep places of the earth. You never get lost in caves or mines if you have either seen an accurate map of them or have been through them before. Furthermore, you are able to scrounge fresh water and food for yourself and as many as five other people each day if you are in a mine or natural caves."
          }
        ]
      },
      {
        "type": "element",
        "tag": "h3",
        "children": [
          {
            "type": "element",
            "tag": "strong",
            "children": [
              {
                "type": "text",
                "text": "Earthspur Miner Personality Traits"
              }
            ]
          }
        ]
      },
      {
        "type": "element",
        "tag": "table",
        "children": [
          {
            "type": "element",
            "tag": "tr",
            "children": [
              {
                "type": "element",
                "tag": "th",
                "children": [
                  {
                    "type": "text",
                    "text": "d8"
                  }
                ]
              },
              {
                "type": "element",
                "tag": "th",
                "children": [
                  {
                    "type": "text",
                    "text": "Personality Trait"
                  }
                ]
              }
            ]
          },
          {
            "type": "element",
            "tag": "tr",
            "children": [
              {
                "type": "element",
                "tag": "td",
                "children": [
                  {
                    "type": "text",
                    "text": "1"
                  }
                ]
              },
              {
                "type": "element",
                "tag": "td",
                "children": [
                  {
                    "type": "text",
                    "text": "Nothing bothers me for long."
                  }
                ]
              }
            ]
          },
          {
            "type": "element",
            "tag": "tr",
            "children": [
              {
                "type": "element",
                "tag": "td",
                "children": [
                  {
                    "type": "text",
                    "text": "2"
                  }
                ]
              },
              {
                "type": "element",
                "tag": "td",
                "children": [
                  {
                    "type": "text",
                    "text": "I hate the horrors of the Underdark with a passion. They took my friends and family and almost got me."
                  }
                ]
              }
            ]
          },
          {
            "type": "element",
            "tag": "tr",
            "children": [
              {
                "type": "element",
                "tag": "td",
                "children": [
                  {
                    "type": "text",
                    "text": "3"
                  }
                ]
              },
              {
                "type": "element",
                "tag": "td",
                "children": [
                  {
                    "type": "text",
                    "text": "Anything worth doing takes time and patience. I have learned to plan and wait for the things I want and to be patient to achieve my goals."
                  }
                ]
              }
            ]
          },
          {
            "type": "element",
            "tag": "tr",
            "children": [
              {
                "type": "element",
                "tag": "td",
                "children": [
                  {
                    "type": "text",
                    "text": "4"
                  }
                ]
              },
              {
                "type": "element",
                "tag": "td",
                "children": [
                  {
                    "type": "text",
                    "text": "I can party with everyone. Whether with dwarves, or goliaths, or deep gnomes, I can find a way to have a good time."
                  }
                ]
              }
            ]
          },
          {
            "type": "element",
            "tag": "tr",
            "children": [
              {
                "type": "element",
                "tag": "td",
                "children": [
                  {
                    "type": "text",
                    "text": "5"
                  }
                ]
              },
              {
                "type": "element",
                "tag": "td",
                "children": [
                  {
                    "type": "text",
                    "text": "I'd rather be mining. This is okay; mining is better."
                  }
                ]
              }
            ]
          },
          {
            "type": "element",
            "tag": "tr",
            "children": [
              {
                "type": "element",
                "tag": "td",
                "children": [
                  {
                    "type": "text",
                    "text": "6"
                  }
                ]
              },
              {
                "type": "element",
                "tag": "td",
                "children": [
                  {
                    "type": "text",
                    "text": "I think that I will stumble upon great riches if I just keep looking."
                  }
                ]
              }
            ]
          },
          {
            "type": "element",
            "tag": "tr",
            "children": [
              {
                "type": "element",
                "tag": "td",
                "children": [
                  {
                    "type": "text",
                    "text": "7"
                  }
                ]
              },
              {
                "type": "element",
                "tag": "td",
                "children": [
                  {
                    "type": "text",
                    "text": "People who don't work with their hands and who live in houses are soft and weak."
                  }
                ]
              }
            ]
          },
          {
            "type": "element",
            "tag": "tr",
            "children": [
              {
                "type": "element",
                "tag": "td",
                "children": [
                  {
                    "type": "text",
                    "text": "8"
                  }
                ]
              },
              {
                "type": "element",
                "tag": "td",
                "children": [
                  {
                    "type": "text",
                    "text": "I wish I were more educated. I look up to people who are."
                  }
                ]
              }
            ]
          }
        ]
      },
      {
        "type": "element",
        "tag": "h3",
        "children": [
          {
            "type": "element",
            "tag": "strong",
            "children": [
              {
                "type": "text",
                "text": "Earthspur Miner Ideals"
              }
            ]
          }
        ]
      },
      {
        "type": "element",
        "tag": "table",
        "children": [
          {
            "type": "element",
            "tag": "tr",
            "children": [
              {
                "type": "element",
                "tag": "th",
                "children": [
                  {
                    "type": "text",
                    "text": "d6"
                  }
                ]
              },
              {
                "type": "element",
                "tag": "th",
                "children": [
                  {
                    "type": "text",
                    "text": "Ideal"
                  }
                ]
              }
            ]
          },
          {
            "type": "element",
            "tag": "tr",
            "children": [
              {
                "type": "element",
                "tag": "td",
                "children": [
                  {
                    "type": "text",
                    "text": "1"
                  }
                ]
              },
              {
                "type": "element",
                "tag": "td",
                "children": [
                  {
                    "type": "element",
                    "tag": "strong",
                    "children": [
                      {
                        "type": "text",
                        "text": "Generosity."
                      }
                    ]
                  },
                  {
                    "type": "text",
                    "text": " The riches of the earth are to be shared by all. (Good)"
                  }
                ]
              }
            ]
          },
          {
            "type": "element",
            "tag": "tr",
            "children": [
              {
                "type": "element",
                "tag": "td",
                "children": [
                  {
                    "type": "text",
                    "text": "2"
                  }
                ]
              },
              {
                "type": "element",
                "tag": "td",
                "children": [
                  {
                    "type": "element",
                    "tag": "strong",
                    "children": [
                      {
                        "type": "text",
                        "text": "Greed."
                      }
                    ]
                  },
                  {
                    "type": "text",
                    "text": " Gems and precious metals, I want them all for myself. (Evil)"
                  }
                ]
              }
            ]
          },
          {
            "type": "element",
            "tag": "tr",
            "children": [
              {
                "type": "element",
                "tag": "td",
                "children": [
                  {
                    "type": "text",
                    "text": "3"
                  }
                ]
              },
              {
                "type": "element",
                "tag": "td",
                "children": [
                  {
                    "type": "element",
                    "tag": "strong",
                    "children": [
                      {
                        "type": "text",
                        "text": "Mooch."
                      }
                    ]
                  },
                  {
                    "type": "text",
                    "text": " Property, schmoperty. If I need it, I take and use it. If I don't, I leave it for someone else. (Chaotic)"
                  }
                ]
              }
            ]
          },
          {
            "type": "element",
            "tag": "tr",
            "children": [
              {
                "type": "element",
                "tag": "td",
                "children": [
                  {
                    "type": "text",
                    "text": "4"
                  }
                ]
              },
              {
                "type": "element",
                "tag": "td",
                "children": [
                  {
                    "type": "element",
                    "tag": "strong",
                    "children": [
                      {
                        "type": "text",
                        "text": "Boundaries."
                      }
                    ]
                  },
                  {
                    "type": "text",
                    "text": " Everything and everyone has its prescribed place; I respect that and expect others to do the same. (Lawful)"
                  }
                ]
              }
            ]
          },
          {
            "type": "element",
            "tag": "tr",
            "children": [
              {
                "type": "element",
                "tag": "td",
                "children": [
                  {
                    "type": "text",
                    "text": "5"
                  }
                ]
              },
              {
                "type": "element",
                "tag": "td",
                "children": [
                  {
                    "type": "element",
                    "tag": "strong",
                    "children": [
                      {
                        "type": "text",
                        "text": "Let it Be."
                      }
                    ]
                  },
                  {
                    "type": "text",
                    "text": " I don't meddle in the affairs of others if I can avoid it. They're none of my business. (Neutral)"
                  }
                ]
              }
            ]
          },
          {
            "type": "element",
            "tag": "tr",
            "children": [
              {
                "type": "element",
                "tag": "td",
                "children": [
                  {
                    "type": "text",
                    "text": "6"
                  }
                ]
              },
              {
                "type": "element",
                "tag": "td",
                "children": [
                  {
                    "type": "element",
                    "tag": "strong",
                    "children": [
                      {
                        "type": "text",
                        "text": "Materialist."
                      }
                    ]
                  },
                  {
                    "type": "text",
                    "text": " I want riches to improve my life. (Any)"
                  }
                ]
              }
            ]
          }
        ]
      },
      {
        "type": "element",
        "tag": "h3",
        "children": [
          {
            "type": "element",
            "tag": "strong",
            "children": [
              {
                "type": "text",
                "text": "Earthspur Miner Bonds"
              }
            ]
          }
        ]
      },
      {
        "type": "element",
        "tag": "table",
        "children": [
          {
            "type": "element",
            "tag": "tr",
            "children": [
              {
                "type": "element",
                "tag": "th",
                "children": [
                  {
                    "type": "text",
                    "text": "d6"
                  }
                ]
              },
              {
                "type": "element",
                "tag": "th",
                "children": [
                  {
                    "type": "text",
                    "text": "Bond"
                  }
                ]
              }
            ]
          },
          {
            "type": "element",
            "tag": "tr",
            "children": [
              {
                "type": "element",
                "tag": "td",
                "children": [
                  {
                    "type": "text",
                    "text": "1"
                  }
                ]
              },
              {
                "type": "element",
                "tag": "td",
                "children": [
                  {
                    "type": "text",
                    "text": "The people of the Earthspur mines are my family. I will do anything to protect them."
                  }
                ]
              }
            ]
          },
          {
            "type": "element",
            "tag": "tr",
            "children": [
              {
                "type": "element",
                "tag": "td",
                "children": [
                  {
                    "type": "text",
                    "text": "2"
                  }
                ]
              },
              {
                "type": "element",
                "tag": "td",
                "children": [
                  {
                    "type": "text",
                    "text": "A deep gnome saved my life when I was injured and alone. I owe his people a great debt."
                  }
                ]
              }
            ]
          },
          {
            "type": "element",
            "tag": "tr",
            "children": [
              {
                "type": "element",
                "tag": "td",
                "children": [
                  {
                    "type": "text",
                    "text": "3"
                  }
                ]
              },
              {
                "type": "element",
                "tag": "td",
                "children": [
                  {
                    "type": "text",
                    "text": "I must behold and preserve the natural beauty of places below the earth."
                  }
                ]
              }
            ]
          },
          {
            "type": "element",
            "tag": "tr",
            "children": [
              {
                "type": "element",
                "tag": "td",
                "children": [
                  {
                    "type": "text",
                    "text": "4"
                  }
                ]
              },
              {
                "type": "element",
                "tag": "td",
                "children": [
                  {
                    "type": "text",
                    "text": "Gems hold a special fascination for me, more than gold, land, magic, or power."
                  }
                ]
              }
            ]
          },
          {
            "type": "element",
            "tag": "tr",
            "children": [
              {
                "type": "element",
                "tag": "td",
                "children": [
                  {
                    "type": "text",
                    "text": "5"
                  }
                ]
              },
              {
                "type": "element",
                "tag": "td",
                "children": [
                  {
                    "type": "text",
                    "text": "I want to explore new depths and scale new heights."
                  }
                ]
              }
            ]
          },
          {
            "type": "element",
            "tag": "tr",
            "children": [
              {
                "type": "element",
                "tag": "td",
                "children": [
                  {
                    "type": "text",
                    "text": "6"
                  }
                ]
              },
              {
                "type": "element",
                "tag": "td",
                "children": [
                  {
                    "type": "text",
                    "text": "Someday I'm going to find the motherlode, then I'll spend the rest of my life in luxury."
                  }
                ]
              }
            ]
          }
        ]
      },
      {
        "type": "element",
        "tag": "h3",
        "children": [
          {
            "type": "element",
            "tag": "strong",
            "children": [
              {
                "type": "text",
                "text": "Earthspur Miner Flaws"
              }
            ]
          }
        ]
      },
      {
        "type": "element",
        "tag": "table",
        "children": [
          {
            "type": "element",
            "tag": "tr",
            "children": [
              {
                "type": "element",
                "tag": "th",
                "children": [
                  {
                    "type": "text",
                    "text": "d6"
                  }
                ]
              },
              {
                "type": "element",
                "tag": "th",
                "children": [
                  {
                    "type": "text",
                    "text": "Flaw"
                  }
                ]
              }
            ]
          },
          {
            "type": "element",
            "tag": "tr",
            "children": [
              {
                "type": "element",
                "tag": "td",
                "children": [
                  {
                    "type": "text",
                    "text": "1"
                  }
                ]
              },
              {
                "type": "element",
                "tag": "td",
                "children": [
                  {
                    "type": "text",
                    "text": "I'm uncomfortable spending time under the open sky. I'd rather be indoors or underground."
                  }
                ]
              }
            ]
          },
          {
            "type": "element",
            "tag": "tr",
            "children": [
              {
                "type": "element",
                "tag": "td",
                "children": [
                  {
                    "type": "text",
                    "text": "2"
                  }
                ]
              },
              {
                "type": "element",
                "tag": "td",
                "children": [
                  {
                    "type": "text",
                    "text": "I'm not used to being around other people much and sometimes get grouchy about it."
                  }
                ]
              }
            ]
          },
          {
            "type": "element",
            "tag": "tr",
            "children": [
              {
                "type": "element",
                "tag": "td",
                "children": [
                  {
                    "type": "text",
                    "text": "3"
                  }
                ]
              },
              {
                "type": "element",
                "tag": "td",
                "children": [
                  {
                    "type": "text",
                    "text": "Good tools are more reliable than people. In a cave-in, I would save a sturdy pick before a stranger."
                  }
                ]
              }
            ]
          },
          {
            "type": "element",
            "tag": "tr",
            "children": [
              {
                "type": "element",
                "tag": "td",
                "children": [
                  {
                    "type": "text",
                    "text": "4"
                  }
                ]
              },
              {
                "type": "element",
                "tag": "td",
                "children": [
                  {
                    "type": "text",
                    "text": "I jealously guard my secrets, because I think others will take advantage of me if they learn what I know."
                  }
                ]
              }
            ]
          },
          {
            "type": "element",
            "tag": "tr",
            "children": [
              {
                "type": "element",
                "tag": "td",
                "children": [
                  {
                    "type": "text",
                    "text": "5"
                  }
                ]
              },
              {
                "type": "element",
                "tag": "td",
                "children": [
                  {
                    "type": "text",
                    "text": "I am obsessed with getting rich. I always have a scheme brewing for making it big."
                  }
                ]
              }
            ]
          },
          {
            "type": "element",
            "tag": "tr",
            "children": [
              {
                "type": "element",
                "tag": "td",
                "children": [
                  {
                    "type": "text",
                    "text": "6"
                  }
                ]
              },
              {
                "type": "element",
                "tag": "td",
                "children": [
                  {
                    "type": "text",
                    "text": "I'm afraid of the dark."
                  }
                ]
              }
            ]
          }
        ]
      }
    ],
    "html": "<div id=\"page-content\">\n<p>Source: Mulmaster Bonds and Backgrounds</p>\n<p>You are a down-on-your-luck miner from the Earthspur Mountains who is no stranger to hardship. You have spent a great deal of time living among the dwarves, goliaths, and denizens of the Underdark who also work mines in the area. At this point, you're just as comfortable working underground as above. You know how to read a seam, dicker for supplies with the deep gnomes, party with dwarves, and find your way back to the surface afterward. Unfortunately, you haven't struck it rich… yet. Although you've come to Mulmaster looking for work, the tall peaks and deep mines of the Earthspurs still call to you.</p>\n<p><strong>Skill Proficiencies:</strong> Athletics, Survival<br/>\n<strong>Languages:</strong> Dwarven and Undercommon<br/>\n<strong>Equipment:</strong> A shovelValue:2gp Weight:5lbs or a miner's pickValue:2gp Weight:10lbs, a block and tackleValue:1gp Weight:5lbs, a climber's kitContents:<br/>\nSpecial Pitons<br/>\nBoot Tips<br/>\nGloves<br/>\nHarness, a set of common clothesValue:5sp Weight:3lbs, and a pouchValue:5sp Weight:1lb containing 5gp</p>\n<h2>Feature: Deep Miner</h2>\n<p>You are used to navigating the deep places of the earth. You never get lost in caves or mines if you have either seen an accurate map of them or have been through them before. Furthermore, you are able to scrounge fresh water and food for yourself and as many as five other people each day if you are in a mine or natural caves.</p>\n<h3><strong>Earthspur Miner Personality Traits</strong></h3>\n<table>\n<tr>\n<th>d8</th>\n<th>Personality Trait</th>\n</tr>\n<tr>\n<td>1</td>\n<td>Nothing bothers me for long.</td>\n</tr>\n<tr>\n<td>2</td>\n<td>I hate the horrors of the Underdark with a passion. They took my friends and family and almost got me.</td>\n</tr>\n<tr>\n<td>3</td>\n<td>Anything worth doing takes time and patience. I have learned to plan and wait for the things I want and to be patient to achieve my goals.</td>\n</tr>\n<tr>\n<td>4</td>\n<td>I can party with everyone. Whether with dwarves, or goliaths, or deep gnomes, I can find a way to have a good time.</td>\n</tr>\n<tr>\n<td>5</td>\n<td>I'd rather be mining. This is okay; mining is better.</td>\n</tr>\n<tr>\n<td>6</td>\n<td>I think that I will stumble upon great riches if I just keep looking.</td>\n</tr>\n<tr>\n<td>7</td>\n<td>People who don't work with their hands and who live in houses are soft and weak.</td>\n</tr>\n<tr>\n<td>8</td>\n<td>I wish I were more educated. I look up to people who are.</td>\n</tr>\n</table>\n<h3><strong>Earthspur Miner Ideals</strong></h3>\n<table>\n<tr>\n<th>d6</th>\n<th>Ideal</th>\n</tr>\n<tr>\n<td>1</td>\n<td><strong>Generosity.</strong> The riches of the earth are to be shared by all. (Good)</td>\n</tr>\n<tr>\n<td>2</td>\n<td><strong>Greed.</strong> Gems and precious metals, I want them all for myself. (Evil)</td>\n</tr>\n<tr>\n<td>3</td>\n<td><strong>Mooch.</strong> Property, schmoperty. If I need it, I take and use it. If I don't, I leave it for someone else. (Chaotic)</td>\n</tr>\n<tr>\n<td>4</td>\n<td><strong>Boundaries.</strong> Everything and everyone has its prescribed place; I respect that and expect others to do the same. (Lawful)</td>\n</tr>\n<tr>\n<td>5</td>\n<td><strong>Let it Be.</strong> I don't meddle in the affairs of others if I can avoid it. They're none of my business. (Neutral)</td>\n</tr>\n<tr>\n<td>6</td>\n<td><strong>Materialist.</strong> I want riches to improve my life. (Any)</td>\n</tr>\n</table>\n<h3><strong>Earthspur Miner Bonds</strong></h3>\n<table>\n<tr>\n<th>d6</th>\n<th>Bond</th>\n</tr>\n<tr>\n<td>1</td>\n<td>The people of the Earthspur mines are my family. I will do anything to protect them.</td>\n</tr>\n<tr>\n<td>2</td>\n<td>A deep gnome saved my life when I was injured and alone. I owe his people a great debt.</td>\n</tr>\n<tr>\n<td>3</td>\n<td>I must behold and preserve the natural beauty of places below the earth.</td>\n</tr>\n<tr>\n<td>4</td>\n<td>Gems hold a special fascination for me, more than gold, land, magic, or power.</td>\n</tr>\n<tr>\n<td>5</td>\n<td>I want to explore new depths and scale new heights.</td>\n</tr>\n<tr>\n<td>6</td>\n<td>Someday I'm going to find the motherlode, then I'll spend the rest of my life in luxury.</td>\n</tr>\n</table>\n<h3><strong>Earthspur Miner Flaws</strong></h3>\n<table>\n<tr>\n<th>d6</th>\n<th>Flaw</th>\n</tr>\n<tr>\n<td>1</td>\n<td>I'm uncomfortable spending time under the open sky. I'd rather be indoors or underground.</td>\n</tr>\n<tr>\n<td>2</td>\n<td>I'm not used to being around other people much and sometimes get grouchy about it.</td>\n</tr>\n<tr>\n<td>3</td>\n<td>Good tools are more reliable than people. In a cave-in, I would save a sturdy pick before a stranger.</td>\n</tr>\n<tr>\n<td>4</td>\n<td>I jealously guard my secrets, because I think others will take advantage of me if they learn what I know.</td>\n</tr>\n<tr>\n<td>5</td>\n<td>I am obsessed with getting rich. I always have a scheme brewing for making it big.</td>\n</tr>\n<tr>\n<td>6</td>\n<td>I'm afraid of the dark.</td>\n</tr>\n</table>\n</div>"
  }
}