{
  "kind": "LINEAGE",
  "group": "Setting Specific Lineages",
  "setting": "Spelljammer",
  "slug": "elf-astral",
  "url": "https://dnd5e.wikidot.com/lineage:elf-astral",
  "page_title": "elf-astral",
  "content": {
    "format": "html-structure-tree",
    "allowed_tags": [
      "b",
      "blockquote",
      "br",
      "code",
      "em",
      "h1",
      "h2",
      "h3",
      "h4",
      "h5",
      "h6",
      "hr",
      "i",
      "li",
      "ol",
      "p",
      "pre",
      "strong",
      "table",
      "tbody",
      "td",
      "tfoot",
      "th",
      "thead",
      "tr",
      "ul"
    ],
    "tree": [
      {
        "type": "element",
        "tag": "p",
        "children": [
          {
            "type": "text",
            "text": "Source: Astral Adventurer's Guide"
          }
        ]
      },
      {
        "type": "element",
        "tag": "p",
        "children": [
          {
            "type": "element",
            "tag": "strong",
            "children": [
              {
                "type": "element",
                "tag": "em",
                "children": [
                  {
                    "type": "text",
                    "text": "Long ago, groups of elves ventured from the Feywild to the Astral Plane to be closer to their gods. Life in the Silver Void has imbued their souls with a spark of divine light. That light manifests as a starry gleam in an astral elf's eyes."
                  }
                ]
              }
            ]
          }
        ]
      },
      {
        "type": "element",
        "tag": "p",
        "children": [
          {
            "type": "element",
            "tag": "strong",
            "children": [
              {
                "type": "element",
                "tag": "em",
                "children": [
                  {
                    "type": "text",
                    "text": "Because nothing ages on the Astral Plane, astral elves who inhabit that plane can be very old, and their longevity gives them an unusual perspective on the passage of time. Some are prone to melancholy, while others might display an absence of feeling. Many look for creative ways to occupy themselves. Whether they choose to live in quiet contemplation or strike out to explore the reaches of the multiverse, astral elves tend to see things through the lens of time as having little or no meaning to them. Astral elves who don't dwell in the Astral Plane can live to be more than 750 years old."
                  }
                ]
              }
            ]
          }
        ]
      },
      {
        "type": "element",
        "tag": "ul",
        "children": [
          {
            "type": "element",
            "tag": "li",
            "children": [
              {
                "type": "element",
                "tag": "em",
                "children": [
                  {
                    "type": "element",
                    "tag": "strong",
                    "children": [
                      {
                        "type": "text",
                        "text": "Ability Score Increase."
                      }
                    ]
                  }
                ]
              },
              {
                "type": "text",
                "text": " Increase one ability score by 2, and increase a different one by 1, or increase three different scores by 1."
              }
            ]
          }
        ]
      },
      {
        "type": "element",
        "tag": "ul",
        "children": [
          {
            "type": "element",
            "tag": "li",
            "children": [
              {
                "type": "element",
                "tag": "em",
                "children": [
                  {
                    "type": "element",
                    "tag": "strong",
                    "children": [
                      {
                        "type": "text",
                        "text": "Creature Type."
                      }
                    ]
                  }
                ]
              },
              {
                "type": "text",
                "text": " You are a Humanoid. You are also considered an elf for any prerequisite or effect that requires you to be an elf."
              }
            ]
          }
        ]
      },
      {
        "type": "element",
        "tag": "ul",
        "children": [
          {
            "type": "element",
            "tag": "li",
            "children": [
              {
                "type": "element",
                "tag": "em",
                "children": [
                  {
                    "type": "element",
                    "tag": "strong",
                    "children": [
                      {
                        "type": "text",
                        "text": "Size."
                      }
                    ]
                  }
                ]
              },
              {
                "type": "text",
                "text": " You are Medium."
              }
            ]
          }
        ]
      },
      {
        "type": "element",
        "tag": "ul",
        "children": [
          {
            "type": "element",
            "tag": "li",
            "children": [
              {
                "type": "element",
                "tag": "em",
                "children": [
                  {
                    "type": "element",
                    "tag": "strong",
                    "children": [
                      {
                        "type": "text",
                        "text": "Speed."
                      }
                    ]
                  }
                ]
              },
              {
                "type": "text",
                "text": " Your walking speed is 30 feet."
              }
            ]
          }
        ]
      },
      {
        "type": "element",
        "tag": "ul",
        "children": [
          {
            "type": "element",
            "tag": "li",
            "children": [
              {
                "type": "element",
                "tag": "em",
                "children": [
                  {
                    "type": "element",
                    "tag": "strong",
                    "children": [
                      {
                        "type": "text",
                        "text": "Astral Fire."
                      }
                    ]
                  }
                ]
              },
              {
                "type": "text",
                "text": " You know one of the following cantrips of your choice: "
              },
              {
                "type": "text",
                "text": "Dancing Lights"
              },
              {
                "type": "text",
                "text": ", "
              },
              {
                "type": "text",
                "text": "Light"
              },
              {
                "type": "text",
                "text": ", or "
              },
              {
                "type": "text",
                "text": "Sacred Flame"
              },
              {
                "type": "text",
                "text": ". Intelligence, Wisdom, or Charisma is your spellcasting ability for it (choose when you select this race)."
              }
            ]
          }
        ]
      },
      {
        "type": "element",
        "tag": "ul",
        "children": [
          {
            "type": "element",
            "tag": "li",
            "children": [
              {
                "type": "element",
                "tag": "em",
                "children": [
                  {
                    "type": "element",
                    "tag": "strong",
                    "children": [
                      {
                        "type": "text",
                        "text": "Darkvision."
                      }
                    ]
                  }
                ]
              },
              {
                "type": "text",
                "text": " You can see dim light within 60 feet of yourself as if it were bright light, and in darkness as if it were dim light. You discern colors in darkness only as shades of gray."
              }
            ]
          }
        ]
      },
      {
        "type": "element",
        "tag": "ul",
        "children": [
          {
            "type": "element",
            "tag": "li",
            "children": [
              {
                "type": "element",
                "tag": "em",
                "children": [
                  {
                    "type": "element",
                    "tag": "strong",
                    "children": [
                      {
                        "type": "text",
                        "text": "Fey Ancestry."
                      }
                    ]
                  }
                ]
              },
              {
                "type": "text",
                "text": " You have advantage on saving throws you make to avoid or end the charmed condition on yourself."
              }
            ]
          }
        ]
      },
      {
        "type": "element",
        "tag": "ul",
        "children": [
          {
            "type": "element",
            "tag": "li",
            "children": [
              {
                "type": "element",
                "tag": "em",
                "children": [
                  {
                    "type": "element",
                    "tag": "strong",
                    "children": [
                      {
                        "type": "text",
                        "text": "Keen Senses."
                      }
                    ]
                  }
                ]
              },
              {
                "type": "text",
                "text": " You have proficiency in the Perception skill."
              }
            ]
          }
        ]
      },
      {
        "type": "element",
        "tag": "ul",
        "children": [
          {
            "type": "element",
            "tag": "li",
            "children": [
              {
                "type": "element",
                "tag": "em",
                "children": [
                  {
                    "type": "element",
                    "tag": "strong",
                    "children": [
                      {
                        "type": "text",
                        "text": "Starlight Step."
                      }
                    ]
                  }
                ]
              },
              {
                "type": "text",
                "text": " As a bonus action, you can magically teleport up to 30 feet to an unoccupied space you can see. You can use this trait a number of times equal to your proficiency bonus, and you regain all expended uses when you finish a long rest."
              }
            ]
          }
        ]
      },
      {
        "type": "element",
        "tag": "ul",
        "children": [
          {
            "type": "element",
            "tag": "li",
            "children": [
              {
                "type": "element",
                "tag": "em",
                "children": [
                  {
                    "type": "element",
                    "tag": "strong",
                    "children": [
                      {
                        "type": "text",
                        "text": "Astral Trance."
                      }
                    ]
                  }
                ]
              },
              {
                "type": "text",
                "text": " You don't need to sleep, and magic can't put you to sleep. You can finish a long rest in 4 hours if you spend those hours in a trancelike meditation, during which you remain conscious. Whenever you finish this trance, you gain proficiency in one skill of your choice and with one weapon or tool of your choice, selected from the "
              },
              {
                "type": "element",
                "tag": "em",
                "children": [
                  {
                    "type": "text",
                    "text": "Player's Handbook"
                  }
                ]
              },
              {
                "type": "text",
                "text": ". You magically acquire these proficiencies by drawing them from shared elven memory and the experiences of entities on the Astral Plane, and you retain them until you finish your next long rest."
              }
            ]
          }
        ]
      },
      {
        "type": "element",
        "tag": "ul",
        "children": [
          {
            "type": "element",
            "tag": "li",
            "children": [
              {
                "type": "element",
                "tag": "em",
                "children": [
                  {
                    "type": "element",
                    "tag": "strong",
                    "children": [
                      {
                        "type": "text",
                        "text": "Languages."
                      }
                    ]
                  }
                ]
              },
              {
                "type": "text",
                "text": " You can speak, read, and write Common and one other language that you and your DM agree is appropriate."
              }
            ]
          }
        ]
      }
    ],
    "html": "<div id=\"page-content\">\n<p>Source: Astral Adventurer's Guide</p>\n<p><strong><em>Long ago, groups of elves ventured from the Feywild to the Astral Plane to be closer to their gods. Life in the Silver Void has imbued their souls with a spark of divine light. That light manifests as a starry gleam in an astral elf's eyes.</em></strong></p>\n<p><strong><em>Because nothing ages on the Astral Plane, astral elves who inhabit that plane can be very old, and their longevity gives them an unusual perspective on the passage of time. Some are prone to melancholy, while others might display an absence of feeling. Many look for creative ways to occupy themselves. Whether they choose to live in quiet contemplation or strike out to explore the reaches of the multiverse, astral elves tend to see things through the lens of time as having little or no meaning to them. Astral elves who don't dwell in the Astral Plane can live to be more than 750 years old.</em></strong></p>\n<ul>\n<li><em><strong>Ability Score Increase.</strong></em> Increase one ability score by 2, and increase a different one by 1, or increase three different scores by 1.</li>\n</ul>\n<ul>\n<li><em><strong>Creature Type.</strong></em> You are a Humanoid. You are also considered an elf for any prerequisite or effect that requires you to be an elf.</li>\n</ul>\n<ul>\n<li><em><strong>Size.</strong></em> You are Medium.</li>\n</ul>\n<ul>\n<li><em><strong>Speed.</strong></em> Your walking speed is 30 feet.</li>\n</ul>\n<ul>\n<li><em><strong>Astral Fire.</strong></em> You know one of the following cantrips of your choice: Dancing Lights, Light, or Sacred Flame. Intelligence, Wisdom, or Charisma is your spellcasting ability for it (choose when you select this race).</li>\n</ul>\n<ul>\n<li><em><strong>Darkvision.</strong></em> You can see dim light within 60 feet of yourself as if it were bright light, and in darkness as if it were dim light. You discern colors in darkness only as shades of gray.</li>\n</ul>\n<ul>\n<li><em><strong>Fey Ancestry.</strong></em> You have advantage on saving throws you make to avoid or end the charmed condition on yourself.</li>\n</ul>\n<ul>\n<li><em><strong>Keen Senses.</strong></em> You have proficiency in the Perception skill.</li>\n</ul>\n<ul>\n<li><em><strong>Starlight Step.</strong></em> As a bonus action, you can magically teleport up to 30 feet to an unoccupied space you can see. You can use this trait a number of times equal to your proficiency bonus, and you regain all expended uses when you finish a long rest.</li>\n</ul>\n<ul>\n<li><em><strong>Astral Trance.</strong></em> You don't need to sleep, and magic can't put you to sleep. You can finish a long rest in 4 hours if you spend those hours in a trancelike meditation, during which you remain conscious. Whenever you finish this trance, you gain proficiency in one skill of your choice and with one weapon or tool of your choice, selected from the <em>Player's Handbook</em>. You magically acquire these proficiencies by drawing them from shared elven memory and the experiences of entities on the Astral Plane, and you retain them until you finish your next long rest.</li>\n</ul>\n<ul>\n<li><em><strong>Languages.</strong></em> You can speak, read, and write Common and one other language that you and your DM agree is appropriate.</li>\n</ul>\n</div>"
  }
}